sahutorepol/Errors.py
sahutorepol/TypeHints.py
sahutorepol/Types.py
sahutorepol/__init__.py
sahutorepol/__main__.py
sahutorepol/debug.py
sahutorepol/main.py
sahutorepol/profiling.py
sahutorepol/sahutorepol.py
sahutorepol/shell.py
simple_warnings/__init__.py
SaHuTOrEPoLPy-0.0.5.dist-info/LICENSE.md
SaHuTOrEPoLPy-0.0.5.dist-info/METADATA
SaHuTOrEPoLPy-0.0.5.dist-info/WHEEL
SaHuTOrEPoLPy-0.0.5.dist-info/entry_points.txt
SaHuTOrEPoLPy-0.0.5.dist-info/top_level.txt
SaHuTOrEPoLPy-0.0.5.dist-info/RECORD
