Metadata-Version: 2.1
Name: SaHuTOrEPoLPy
Version: 0.0.5
Summary: SaHuTOrEPoLPy is a simple interpreter for SaHuTOrEPoL
Home-page: https://github.com/MinekPo1/SaHuTOrEPoLPy
Author: MinekPo1
Author-email: minekpo1@gmail.com
License: fafol
Platform: UNKNOWN
Classifier: License :: Free To Use But Restricted
Classifier: Programming Language :: Python :: 3
Classifier: Programming Language :: Python :: 3.10
License-File: LICENSE.md
Requires-Dist: typing
Requires-Dist: click
